ParaTkinter/__init__.py
ParaTkinter/parallax.py
paratkinter-1.1.0.dist-info/licenses/LICENSE
paratkinter-1.1.0.dist-info/METADATA
paratkinter-1.1.0.dist-info/WHEEL
paratkinter-1.1.0.dist-info/top_level.txt
paratkinter-1.1.0.dist-info/RECORD
