Metadata-Version: 2.4
Name: paratkinter
Version: 1.1.0
Summary: Add parallax effects and UI enhancements to (custom)tkinter apps
Author-email: Kabir Tiwari <kabir.tiwari@outlook.com>
License: MIT
Requires-Python: >=3.8
License-File: LICENSE
Requires-Dist: customtkinter
Dynamic: license-file
